zuulclient/__init__.py
zuulclient/version.py
zuulclient/api/__init__.py
zuulclient/cmd/__init__.py
zuulclient/utils/__init__.py
zuulclient/utils/formatters.py
zuul_client-10.0.0.dist-info/AUTHORS
zuul_client-10.0.0.dist-info/LICENSE
zuul_client-10.0.0.dist-info/METADATA
zuul_client-10.0.0.dist-info/WHEEL
zuul_client-10.0.0.dist-info/entry_points.txt
zuul_client-10.0.0.dist-info/pbr.json
zuul_client-10.0.0.dist-info/top_level.txt
zuul_client-10.0.0.dist-info/RECORD
