Metadata-Version: 2.1
Name: zuul-client
Version: 10.0.0
Summary: A client for the Zuul Gating System
Home-page: https://zuul-ci.org/
Author: Zuul Team
Author-email: zuul-discuss@lists.zuul-ci.org
License: Apache License, Version 2.0
Project-URL: Browse Source, https://opendev.org/zuul/zuul-client
Project-URL: Bug Reporting, https://storyboard.openstack.org/#!/project/zuul/zuul-client
Project-URL: Documentation, https://zuul-ci.org/docs/zuul-client
Project-URL: Git Clone URL, https://opendev.org/zuul/zuul-client
Project-URL: License Texts, https://opendev.org/zuul/zuul-client/src/branch/master/LICENSE
Project-URL: Release Notes, https://zuul-ci.org/docs/zuul-client/releasenotes.html
Keywords: gating continuous integration delivery deployment commandline
Platform: UNKNOWN
Classifier: Environment :: Console
Classifier: Intended Audience :: Information Technology
Classifier: Intended Audience :: System Administrators
Classifier: License :: OSI Approved :: Apache Software License
Classifier: Operating System :: OS Independent
Classifier: Programming Language :: Python
Classifier: Programming Language :: Python :: 3
Classifier: Programming Language :: Python :: 3.8
Classifier: Programming Language :: Python :: 3.9
Classifier: Programming Language :: Python :: 3.10
Classifier: Programming Language :: Python :: 3 :: Only
Classifier: Topic :: Software Development :: Quality Assurance
Classifier: Topic :: Software Development :: Testing
Classifier: Topic :: Software Development :: Version Control :: Git
Classifier: Topic :: System :: Systems Administration
Classifier: Topic :: Utilities
Requires-Python: >=3.8
License-File: LICENSE
Requires-Dist: PrettyTable
Requires-Dist: pbr (>=1.1.0)
Requires-Dist: python-dateutil (>=2.7.0)
Requires-Dist: pyyaml
Requires-Dist: requests
Requires-Dist: setuptools
Requires-Dist: urllib3 (!=1.25.4,!=1.25.5)
